agify/__init__.py
agify/wrappers.py
agify-0.2.0.dist-info/LICENSE
agify-0.2.0.dist-info/METADATA
agify-0.2.0.dist-info/WHEEL
agify-0.2.0.dist-info/top_level.txt
agify-0.2.0.dist-info/RECORD
